codegen/__init__.py
codegen/conf/add/.eslintrc.js
codegen/conf/add/.prettierrc
codegen/conf/create/create.yaml
codegen/conf/pyproject.toml
codegen/core/__init__.py
codegen/core/log.py
codegen/core/params.py
codegen/main.py
codegen/util/__init__.py
codegen/util/error.py
codegen/util/file_folder_util.py
oliver_codegen-0.1.6.dist-info/entry_points.txt
oliver_codegen-0.1.6.dist-info/LICENSE
oliver_codegen-0.1.6.dist-info/METADATA
oliver_codegen-0.1.6.dist-info/WHEEL
oliver_codegen-0.1.6.dist-info/RECORD
