Metadata-Version: 2.1
Name: oliver-codegen
Version: 0.1.6
Summary: 项目代码框架快速生成脚手架
Home-page: https://github.com/lifefossil/oliver-codegen
Keywords: codegen,oliver-codegen
Author: oliver
Author-email: lifefossil@outlook.com
Requires-Python: >=3.11
Classifier: Programming Language :: Python :: 3
Classifier: Programming Language :: Python :: 3.11
Classifier: Programming Language :: Python :: 3.12
Requires-Dist: gitpython (>=3.1.42,<4.0.0)
Requires-Dist: pyyaml (>=6.0.1,<7.0.0)
Requires-Dist: toml (>=0.10.2,<0.11.0)
Project-URL: Repository, https://github.com/lifefossil/oliver-codegen
